dec3to8/dec3to8.v
//Decoder Model
module decoder(
    output [7:0] o,
    input enb_,
    input [2:0] sel
);

    reg [7:0] o;
    always @ (enb_ or sel)
        if (enb_)
            o = 8'b11111111;
        else
            case (sel)
                3'b000: o = 8'b11111110;
                3'b001: o = 8'b11111101;
                3'b010: o = 8'b11111011;
                3'b011: o = 8'b11110111;
                3'b100: o = 8'b11101111;
                3'b101: o = 8'b11011111;
                3'b110: o = 8'b10111111;
                3'b111: o = 8'b01111111;
                default: o = 8'bx;
            endcase   
endmodule

dec3to8/dec3to8_tb.v
 //Decoder Testbench
 `timescale 1ns/100ps
 `include "dec3to8.v"

 module dec3to8_tb();
 reg [2:0] sel;
 reg enb_;
 wire [7:0] o;

 decoder idecoder(o, enb_, sel);
 initial
    begin
    $dumpfile("dec3to8.vcd");
    $dumpvars(0, dec3to8_tb);
      enb_ = 1;
      sel = 3'b000; #10;
      enb_ = 0;
      sel = 3'b000; #10;
      sel = 3'b001; #10;
      sel = 3'b010; #10;
      sel = 3'b011; #10;
      sel = 3'b100; #10;
      sel = 3'b101; #10;
      sel = 3'b110; #10;
      sel = 3'b111; #10;
      $finish;
    end
endmodule

dec3to8/dec3to8.vcd
$date
	Fri May 11 19:19:58 2018
$end
$version
	Icarus Verilog
$end
$timescale
	100ps
$end
$scope module dec3to8_tb $end
$var wire 8 ! o [7:0] $end
$var reg 1 " enb_ $end
$var reg 3 # sel [2:0] $end
$scope module idecoder $end
$var wire 1 " enb_ $end
$var wire 3 $ sel [2:0] $end
$var reg 8 % o [7:0] $end
$upscope $end
$upscope $end
$enddefinitions $end
#0
$dumpvars
b11111111 %
b0 $
b0 #
1"
b11111111 !
$end
#100
b11111110 !
b11111110 %
0"
#200
b11111101 !
b11111101 %
b1 #
b1 $
#300
b11111011 !
b11111011 %
b10 #
b10 $
#400
b11110111 !
b11110111 %
b11 #
b11 $
#500
b11101111 !
b11101111 %
b100 #
b100 $
#600
b11011111 !
b11011111 %
b101 #
b101 $
#700
b10111111 !
b10111111 %
b110 #
b110 $
#800
b1111111 !
b1111111 %
b111 #
b111 $
