2x1mux/etmux2x1.v
//Level Triggered 2X1 MUX Model
module etMux(
    input a,
    input b,
    input sel,
    input clk,
    output out
);
    reg out;
    always @(posedge clk)
    begin
      if (sel)
        out = a;       
      else
        out = b;
    end
endmodule

2x1mux/etmux2x1_tb.v
// 2X1 MUX TestBench
`timescale 1s/100ms
`include "etmux2x1.v"

module TwoOneMux_tb();
reg a, b, sel, clk;
wire out;

etMux ietMux(a, b, sel, clk, out);
initial
begin
  $monitor("a=%b, b=%b, sell=%b, clk=%b, out=%b", a, b, sel, clk, out);
  $dumpfile("EdgeTriggeredMux.vcd");
  $dumpvars(0, TwoOneMux_tb);
  a = 0; b = 0; sel = 0; #10;
  a = 0; b = 1; sel = 0; #10;
  a = 1; b = 0; sel = 0; #10;
  a = 1; b = 1; sel = 0; #10;
  a = 0; b = 0; sel = 1; #10;
  a = 0; b = 1; sel = 1; #10;
  a = 1; b = 0; sel = 1; #10;
  a = 1; b = 1; sel = 1; #10;
  $finish;
end
initial
begin
  clk = 0;
end
always begin
#5; clk = ~clk;
end
endmodule

2x1mux/EdgeTriggeredMux.vcd
$date
	Sat May 12 08:28:59 2018
$end
$version
	Icarus Verilog
$end
$timescale
	100ms
$end
$scope module TwoOneMux_tb $end
$var wire 1 ! out $end
$var reg 1 " a $end
$var reg 1 # b $end
$var reg 1 $ clk $end
$var reg 1 % sel $end
$scope module ietMux $end
$var wire 1 " a $end
$var wire 1 # b $end
$var wire 1 $ clk $end
$var wire 1 % sel $end
$var reg 1 ! out $end
$upscope $end
$upscope $end
$enddefinitions $end
#0
$dumpvars
0%
0$
0#
0"
x!
$end
#50
0!
1$
#100
0$
1#
#150
1!
1$
#200
0$
0#
1"
#250
0!
1$
#300
0$
1#
#350
1!
1$
#400
0$
1%
0#
0"
#450
0!
1$
#500
0$
1#
#550
1$
#600
0$
0#
1"
#650
1!
1$
#700
0$
1#
