2x1mux/mux2x1.v
//Level Triggered 2X1 MUX Model
module TwoOneMux(
    input a,
    input b,
    input sel,
    output out
);
    reg out;
    always @(a or b or sel)
    begin
      if (sel)
        out = a;       
      else
        out = b;
    end
endmodule

2x1mux/mux2x1_tb.v
// 2X1 MUX TestBench
`timescale 1s/100ms
`include "mux2x1.v"

module TwoOneMux_tb();
reg a, b, sel;
wire out;

TwoOneMux iTwoOneMux(a, b, sel, out);
initial
begin
  $monitor("a=%b, b=%b, sell=%b, out=%b", a, b, sel, out);
  $dumpfile("LevelTriggeredMux.vcd");
  $dumpvars(0, TwoOneMux_tb);
  a = 0; b = 0; sel = 0; #10;
  a = 0; b = 1; sel = 0; #10;
  a = 1; b = 0; sel = 0; #10;
  a = 1; b = 1; sel = 0; #10;
  a = 0; b = 0; sel = 1; #10;
  a = 0; b = 1; sel = 1; #10;
  a = 1; b = 0; sel = 1; #10;
  a = 1; b = 1; sel = 1; #10;
  $finish;
end
endmodule

2x1mux/LevelTriggeredMux.vcd
$date
	Sat May 12 08:18:56 2018
$end
$version
	Icarus Verilog
$end
$timescale
	100ms
$end
$scope module TwoOneMux_tb $end
$var wire 1 ! out $end
$var reg 1 " a $end
$var reg 1 # b $end
$var reg 1 $ sel $end
$scope module iTwoOneMux $end
$var wire 1 " a $end
$var wire 1 # b $end
$var wire 1 $ sel $end
$var reg 1 ! out $end
$upscope $end
$upscope $end
$enddefinitions $end
#0
$dumpvars
0$
0#
0"
0!
$end
#100
1!
1#
#200
0!
0#
1"
#300
1!
1#
#400
0!
1$
0#
0"
#500
1#
#600
1!
0#
1"
#700
1#
